{"cameraMode":{"drawMode":24,"name":"Light Overlap","section":"Baked Global Illumination"},"sceneLighting":true,"audioPlay":false,"sceneViewState":{"m_AlwaysRefresh":false,"showFog":true,"showSkybox":true,"showFlares":true,"showImageEffects":true,"showParticleSystems":true,"showVisualEffectGraphs":true,"m_FxEnabled":true},"in2DMode":false,"pivot":{"x":30.37543487548828,"y":-2.2644269466400148,"z":29.585391998291017},"rotation":{"x":-0.666359007358551,"y":-0.0037937271408736707,"z":0.0033917371183633806,"w":-0.7456390857696533},"size":44.43574142456055,"orthographic":false}